omars_analysis/.gitignore
omars_analysis/__init__.py
omars_analysis/data/Laser_data.txt
omars_analysis/data/jn_data.txt
omars_analysis/generate_model_matrix_heredity.py
omars_analysis/main.py
omars_analysis/omars_analysis_oop.py
omars_analysis/subset_selection.py
omars_analysis-2.0.1.dist-info/METADATA
omars_analysis-2.0.1.dist-info/WHEEL
omars_analysis-2.0.1.dist-info/RECORD
