Metadata-Version: 2.1
Name: omars-analysis
Version: 2.0.1
Summary: 
Home-page: https://github.com/saif-ismail/omars_analysis/
Author: Mohammed Saif Ismail Hameed
Author-email: saifismailh@gmail.com
Requires-Python: >=3.8,<4.0
Classifier: Programming Language :: Python :: 3
Classifier: Programming Language :: Python :: 3.8
Classifier: Programming Language :: Python :: 3.9
Classifier: Programming Language :: Python :: 3.10
Classifier: Programming Language :: Python :: 3.11
Requires-Dist: numpy (>=1.23.5,<2.0.0)
Requires-Dist: scipy (>=1.9.3,<2.0.0)
Project-URL: Repository, https://github.com/saif-ismail/omars_analysis/
